{"dependencies":[{"name":"/Users/mmoullec/go/src/cdm/react/package.json","includedInParent":true,"mtime":1523881573000},{"name":"react","loc":{"line":6,"column":38}}],"generated":{"js":"\"use strict\";\n\nvar __importDefault = this && this.__importDefault || function (mod) {\n    return mod && mod.__esModule ? mod : { \"default\": mod };\n};\nexports.__esModule = true;\nvar react_1 = __importDefault(require(\"react\"));\nvar App = function App() {\n    return React.createElement(\n        \"div\",\n        null,\n        \"Hello world\"\n    );\n};\nexports[\"default\"] = App;","map":{"mappings":[{"source":"app.tsx","name":null,"original":{"line":1,"column":0},"generated":{"line":7,"column":0}},{"source":"app.tsx","name":null,"original":{"line":1,"column":0},"generated":{"line":7,"column":4}},{"source":"app.tsx","name":null,"original":{"line":1,"column":0},"generated":{"line":7,"column":14}},{"source":"app.tsx","name":null,"original":{"line":1,"column":0},"generated":{"line":7,"column":30}},{"source":"app.tsx","name":null,"original":{"line":1,"column":0},"generated":{"line":7,"column":38}},{"source":"app.tsx","name":null,"original":{"line":1,"column":0},"generated":{"line":7,"column":45}},{"source":"app.tsx","name":null,"original":{"line":1,"column":0},"generated":{"line":7,"column":46}},{"source":"app.tsx","name":null,"original":{"line":1,"column":0},"generated":{"line":7,"column":47}},{"source":"app.tsx","name":null,"original":{"line":3,"column":0},"generated":{"line":8,"column":0}},{"source":"app.tsx","name":null,"original":{"line":3,"column":6},"generated":{"line":8,"column":4}},{"source":"app.tsx","name":null,"original":{"line":3,"column":12},"generated":{"line":8,"column":10}},{"source":"app.tsx","name":null,"original":{"line":3,"column":6},"generated":{"line":8,"column":19}},{"source":"app.tsx","name":null,"original":{"line":3,"column":12},"generated":{"line":8,"column":22}},{"source":"app.tsx","name":null,"original":{"line":3,"column":12},"generated":{"line":8,"column":25}},{"source":"app.tsx","name":null,"original":{"line":4,"column":4},"generated":{"line":9,"column":0}},{"source":"app.tsx","name":null,"original":{"line":4,"column":11},"generated":{"line":9,"column":11}},{"source":"app.tsx","name":null,"original":{"line":4,"column":11},"generated":{"line":10,"column":0}},{"source":"app.tsx","name":null,"original":{"line":4,"column":11},"generated":{"line":11,"column":0}},{"source":"app.tsx","name":null,"original":{"line":4,"column":11},"generated":{"line":12,"column":0}},{"source":"app.tsx","name":null,"original":{"line":4,"column":11},"generated":{"line":13,"column":0}},{"source":"app.tsx","name":null,"original":{"line":4,"column":4},"generated":{"line":13,"column":5}},{"source":"app.tsx","name":null,"original":{"line":5,"column":1},"generated":{"line":14,"column":0}},{"source":"app.tsx","name":null,"original":{"line":3,"column":0},"generated":{"line":14,"column":1}},{"source":"app.tsx","name":null,"original":{"line":7,"column":0},"generated":{"line":15,"column":0}},{"source":"app.tsx","name":null,"original":{"line":7,"column":0},"generated":{"line":15,"column":8}},{"source":"app.tsx","name":null,"original":{"line":7,"column":0},"generated":{"line":15,"column":17}},{"source":"app.tsx","name":null,"original":{"line":7,"column":15},"generated":{"line":15,"column":21}},{"source":"app.tsx","name":null,"original":{"line":7,"column":0},"generated":{"line":15,"column":24}}],"sources":{"app.tsx":"import React, {Component} from \"react\";\n\nconst App = function() {\n    return <div>Hello world</div>\n}\n\nexport default App;"},"lineCount":null}},"hash":"efecef41a8ffb8644fa76c92a0d7928d","cacheData":{"env":{}}}